deDL/__init__.py
deDL/deDL.py
deDL-0.0.1.dist-info/AUTHORS.rst
deDL-0.0.1.dist-info/LICENSE
deDL-0.0.1.dist-info/METADATA
deDL-0.0.1.dist-info/WHEEL
deDL-0.0.1.dist-info/top_level.txt
deDL-0.0.1.dist-info/RECORD
